tivwordnet/__init__.py
tivwordnet/synset.py
tivwordnet/tiv_wordnet.py
tivwordnet/tivwordnet_connector.py
tivwordnet/word.py
tivwordnet/data/tiv_definitions.txt
tivwordnet/data/tiv_synsets.txt
tivwordnet-0.2.0.dist-info/METADATA
tivwordnet-0.2.0.dist-info/WHEEL
tivwordnet-0.2.0.dist-info/top_level.txt
tivwordnet-0.2.0.dist-info/RECORD
