Metadata-Version: 2.1
Name: tivwordnet
Version: 0.2.0
Summary: A semantic network for the Tiv language, modeled after WordNet
Home-page: https://github.com/Dankummzy/tivwordnet
Author: Daniel Kumaga
Author-email: danterkum16@gmail.com
License: UNKNOWN
Platform: UNKNOWN
Classifier: Programming Language :: Python :: 3
Classifier: License :: OSI Approved :: MIT License
Classifier: Operating System :: OS Independent
Requires-Python: >=3.6
